tests/__init__.py
tests/secure.py
tests/test_authenticator.py
tests/test_public_functions.py
tests/test_url_builder.py
tests/utils.py
worldtradingdata/__init__.py
worldtradingdata/authenticator/__init__.py
worldtradingdata/authenticator/base.py
worldtradingdata/public/__init__.py
worldtradingdata/public/base.py
worldtradingdata/public/constants.py
worldtradingdata/url_builder/__init__.py
worldtradingdata/url_builder/base.py
worldtradingdata-0.1.5.dist-info/METADATA
worldtradingdata-0.1.5.dist-info/WHEEL
worldtradingdata-0.1.5.dist-info/top_level.txt
worldtradingdata-0.1.5.dist-info/RECORD
