Metadata-Version: 2.1
Name: worldtradingdata
Version: 0.1.5
Summary: Python SDK to interact with www.worldtradingdata.com
Home-page: https://github.com/staneslevski/WorldTradingDataPythonSDK
Author: Tom Stanley
Author-email: tstanleyuk@icloud.com
License: UNKNOWN
Keywords: finance,trading,data,world trading data
Platform: UNKNOWN
Classifier: Development Status :: 5 - Production/Stable
Classifier: Programming Language :: Python :: 3
Classifier: License :: OSI Approved :: MIT License
Classifier: Operating System :: OS Independent
Classifier: Intended Audience :: Financial and Insurance Industry
Requires-Dist: urllib3 (==1.25.3)
Requires-Dist: pytest (==5.0.1)
